a2y_wxctrls.cp312-win_amd64.pyd
a2y_wxctrls-0.9.3.dist-info/licenses/LICENSE
a2y_wxctrls-0.9.3.dist-info/METADATA
a2y_wxctrls-0.9.3.dist-info/WHEEL
a2y_wxctrls-0.9.3.dist-info/top_level.txt
a2y_wxctrls-0.9.3.dist-info/RECORD
