Metadata-Version: 2.4
Name: a2y_wxctrls
Version: 0.9.3
Summary: 此模块提供一些基于`wxWidgets`的控件，使用`wxFormBuilder`做好布局，代码部分则在`wxtools`里面实现。
Home-page: http://www.kersci.com/a2y/wxctrls.html
Author: Yu Han
Author-email: hanjunyu@163.com
License: Private
Platform: Windows
Platform: Linux
Classifier: Development Status :: 4 - Beta
Classifier: Intended Audience :: Developers
Classifier: License :: Free For Educational Use
Classifier: Programming Language :: Python :: 3.6
Classifier: Operating System :: Microsoft :: Windows :: Windows 10
Classifier: Operating System :: POSIX :: Linux
License-File: LICENSE
Requires-Dist: wxpython>=4.2.0
Requires-Dist: a2y-i18n>=1.0.0
Dynamic: author
Dynamic: author-email
Dynamic: classifier
Dynamic: description
Dynamic: description-content-type
Dynamic: home-page
Dynamic: license
Dynamic: license-file
Dynamic: platform
Dynamic: requires-dist
Dynamic: summary
